AUTHORS.rst
HISTORY.md
README.md
pdfgen/__init__.py
pdfgen/api_async.py
pdfgen/api_sync.py
pdfgen/configuration.py
pdfgen/errors.py
pdfgen/pdfgen.py
pdfgen/source.py
pdfgen/utils.py
pdfgen-1.0.4.dist-info/entry_points.txt
pdfgen-1.0.4.dist-info/LICENSE
pdfgen-1.0.4.dist-info/WHEEL
pdfgen-1.0.4.dist-info/METADATA
pdfgen-1.0.4.dist-info/RECORD
